{"nodes":[{"name":"Beverly Semmes","id":1345,"group":1,"radius":4,"color":"#666"},{"name":"Dirt On Delight: Impulses That Form Clay","id":1724,"group":6,"radius":25},{"name":"Beverly Semmes","id":1852,"group":6,"radius":4},{"name":"ICA@50: Pleasing Artists And Publics Since 1963","id":3580,"group":6,"radius":120},{"name":"ICA@50: Life Drawing Studio","id":5140,"group":7,"radius":7}],"links":[{"source":1345,"target":1724,"weight":9},{"source":1345,"target":1852,"weight":9},{"source":1345,"target":3580,"weight":9},{"source":1345,"target":5140,"weight":9}]}