{"nodes":[{"name":"Alan Shields","id":1357,"group":1,"radius":5,"color":"#666"},{"name":"Drawings: The Pluralist Decade","id":1944,"group":6,"radius":73},{"name":"Masks/ Tents/ Vessels/ Talismans","id":1952,"group":6,"radius":17},{"name":"Painting Drawing and Sculpture of the '60s and the '70s from the Dorthy and Herbert Vogel Collection","id":1969,"group":6,"radius":108},{"name":"Grids","id":1980,"group":6,"radius":29},{"name":"Two Generations of Color Painting","id":1992,"group":6,"radius":25}],"links":[{"source":1357,"target":1944,"weight":9},{"source":1357,"target":1952,"weight":9},{"source":1357,"target":1969,"weight":9},{"source":1357,"target":1980,"weight":9},{"source":1357,"target":1992,"weight":9}]}