{"nodes":[{"name":"Robert Morris/Projects","id":1975,"group":6,"radius":5,"color":"#00D773"},{"name":"Robert Morris","id":1029,"group":1,"radius":13},{"name":"Robert Morris: Projects","id":2204,"group":9,"radius":2},{"name":"Suzanne Delehanty","id":3235,"group":13,"radius":25},{"name":"1974_Robert_Morris_Projects001.jpg","id":4766,"group":12,"radius":1}],"links":[{"source":1975,"target":1029,"weight":9},{"source":1975,"target":2204,"weight":12},{"source":1975,"target":3235,"weight":0},{"source":1975,"target":4766,"weight":6}]}