{"nodes":[{"name":"Two Generations of Color Painting","id":1992,"group":6,"radius":25,"color":"#00D773"},{"name":"Walter Darby Bannard","id":95,"group":1,"radius":2},{"name":"Natvar Bhavsar","id":143,"group":1,"radius":1},{"name":"Gene Davis","id":351,"group":1,"radius":1},{"name":"David Diao","id":380,"group":1,"radius":3},{"name":"Thomas Downing","id":402,"group":1,"radius":1},{"name":"Helen Frankenthaler","id":491,"group":1,"radius":1},{"name":"Sam Gilliam","id":530,"group":1,"radius":2},{"name":"Carl Gliko","id":544,"group":1,"radius":1},{"name":"Ronnie Landfield","id":846,"group":1,"radius":1},{"name":"Morris Louis","id":904,"group":1,"radius":3},{"name":"Howard Mehring","id":989,"group":1,"radius":1},{"name":"Kenneth Noland","id":1085,"group":1,"radius":5},{"name":"Jules Olitski","id":1104,"group":1,"radius":6},{"name":"William Pettet","id":1154,"group":1,"radius":1},{"name":"Larry Poons","id":1184,"group":1,"radius":4},{"name":"Edwin Ruda","id":1284,"group":1,"radius":2},{"name":"Herbert Schiffrin","id":1326,"group":1,"radius":2},{"name":"John Seery","id":1339,"group":1,"radius":1},{"name":"Alan Shields","id":1357,"group":1,"radius":5},{"name":"Two Generations of Color Painting","id":2200,"group":9,"radius":1},{"name":"Helen\u00e9 Aylon","id":3211,"group":1,"radius":1},{"name":"Stephen S. Prokopoff","id":3231,"group":13,"radius":14},{"name":"1970_Two_Generations_of_Color_Painting.jpg","id":4794,"group":12,"radius":2},{"name":"David Diao / *Two Generations of Color Painting*","id":5180,"group":6,"radius":8}],"links":[{"source":1992,"target":95,"weight":9},{"source":1992,"target":143,"weight":9},{"source":1992,"target":351,"weight":9},{"source":1992,"target":380,"weight":9},{"source":1992,"target":402,"weight":9},{"source":1992,"target":491,"weight":9},{"source":1992,"target":530,"weight":9},{"source":1992,"target":544,"weight":9},{"source":1992,"target":846,"weight":9},{"source":1992,"target":904,"weight":9},{"source":1992,"target":989,"weight":9},{"source":1992,"target":1085,"weight":9},{"source":1992,"target":1104,"weight":9},{"source":1992,"target":1154,"weight":9},{"source":1992,"target":1184,"weight":9},{"source":1992,"target":1284,"weight":9},{"source":1992,"target":1326,"weight":9},{"source":1992,"target":1339,"weight":9},{"source":1992,"target":1357,"weight":9},{"source":1992,"target":2200,"weight":12},{"source":1992,"target":3211,"weight":9},{"source":1992,"target":3231,"weight":0},{"source":1992,"target":4794,"weight":6},{"source":1992,"target":5180,"weight":12}]}