{"nodes":[{"name":"An Exhibition to Hear Read","id":2140,"group":7,"radius":4,"color":"#1E1E1E"},{"name":"Jennifer Burris","id":1659,"group":2,"radius":20},{"name":"The Happy Class: Art and design, art and life","id":2715,"group":4,"radius":8},{"name":"077A0541.JPG","id":3535,"group":12,"radius":1},{"name":"077A0538.JPG","id":3536,"group":12,"radius":1}],"links":[{"source":2140,"target":1659,"weight":0},{"source":2140,"target":2715,"weight":12},{"source":2140,"target":3535,"weight":6},{"source":2140,"target":3536,"weight":6}]}