{"nodes":[{"name":"Wild Imaginings: ICA @ 50","id":2484,"group":4,"radius":9,"color":"#fdff89"},{"name":"Richard Torchia","id":1501,"group":1,"radius":3},{"name":"What Is Miranda?","id":2499,"group":4,"radius":3},{"name":"Miranda: salon and bowl","id":2668,"group":12,"radius":1},{"name":"Miranda: Poussin-Et-in-Arcadia-Ego-1638-40_jm","id":2669,"group":12,"radius":1},{"name":"Miranda: Maria_PEW_3_jm","id":2670,"group":12,"radius":1},{"name":"Miranda: Agnes-Martin-catalogueA_jm","id":2671,"group":12,"radius":1},{"name":"Miranda: Ingrid's-wallA_jm","id":2672,"group":12,"radius":1},{"name":"Miranda: Ingrid_Schaffner1A_jm","id":2673,"group":12,"radius":1},{"name":"ICA@50: Pleasing Artists And Publics Since 1963","id":3580,"group":6,"radius":120}],"links":[{"source":2484,"target":1501,"weight":9},{"source":2484,"target":2499,"weight":12},{"source":2484,"target":2668,"weight":6},{"source":2484,"target":2669,"weight":6},{"source":2484,"target":2670,"weight":6},{"source":2484,"target":2671,"weight":6},{"source":2484,"target":2672,"weight":6},{"source":2484,"target":2673,"weight":6},{"source":2484,"target":3580,"weight":12}]}