{"nodes":[{"name":"Art and Activism: ICA Board Member Sarah McEneaney and the Reading Viaduct Project","id":2521,"group":4,"radius":7,"color":"#fdff89"},{"name":"Sarah McEneaney","id":978,"group":1,"radius":8},{"name":"Sarah McEneaney","id":1773,"group":6,"radius":9},{"name":"Miranda: Sarah-on-the-swing-A","id":2516,"group":12,"radius":1},{"name":"Miranda: Building SM","id":2517,"group":12,"radius":1},{"name":"Miranda: City-in-background-CR-A","id":2518,"group":12,"radius":1},{"name":"Miranda: 2-on-swing--Sarah's-photo-A","id":2519,"group":12,"radius":1},{"name":"Miranda: McEneaney-painting-A","id":2520,"group":12,"radius":1}],"links":[{"source":2521,"target":978,"weight":9},{"source":2521,"target":1773,"weight":12},{"source":2521,"target":2516,"weight":6},{"source":2521,"target":2517,"weight":6},{"source":2521,"target":2518,"weight":6},{"source":2521,"target":2519,"weight":6},{"source":2521,"target":2520,"weight":6}]}