{"nodes":[{"name":"Just Right","id":3009,"group":4,"radius":6,"color":"#fdff89"},{"name":"Erin Shirreff","id":1358,"group":1,"radius":4},{"name":"Clyfford Still","id":1444,"group":1,"radius":4},{"name":"Erin Shirreff: Still, Flat, and Far","id":1711,"group":6,"radius":6},{"name":"Clyfford Still","id":2014,"group":6,"radius":9},{"name":"Moon Miranda","id":4289,"group":12,"radius":1},{"name":"Erin Schirreff image","id":4290,"group":12,"radius":1}],"links":[{"source":3009,"target":1358,"weight":9},{"source":3009,"target":1444,"weight":9},{"source":3009,"target":1711,"weight":12},{"source":3009,"target":2014,"weight":12},{"source":3009,"target":4289,"weight":6},{"source":3009,"target":4290,"weight":6}]}