{"nodes":[{"name":"Cobra on Wood","id":3022,"group":4,"radius":7,"color":"#fdff89"},{"name":"R. Crumb","id":328,"group":1,"radius":1},{"name":"Virgil Marti","id":953,"group":1,"radius":14},{"name":"Set Pieces: Curated by Virgil Marti From the Collection of the Philadelphia Museum of Art","id":1710,"group":6,"radius":15},{"name":"R. Crumb's Underground","id":1730,"group":6,"radius":1},{"name":"Virgil Marti: The Flowers of Romance","id":1778,"group":6,"radius":15},{"name":"What Is Miranda?","id":2499,"group":4,"radius":3},{"name":"Snake drawing on wood","id":4285,"group":12,"radius":2}],"links":[{"source":3022,"target":328,"weight":9},{"source":3022,"target":953,"weight":9},{"source":3022,"target":1710,"weight":12},{"source":3022,"target":1730,"weight":12},{"source":3022,"target":1778,"weight":12},{"source":3022,"target":2499,"weight":12},{"source":3022,"target":4285,"weight":6}]}