{"nodes":[{"name":"Polly Apfelbaum","id":48,"group":1,"radius":4,"color":"#666"},{"name":"Polly Apfelbaum","id":1781,"group":6,"radius":6},{"name":"Polly Apfelbaum","id":2335,"group":9,"radius":3},{"name":"Dedication Monuments: Alex Da Corte and First Among Equals","id":2666,"group":4,"radius":17},{"name":"Mission & History","id":3334,"group":10,"radius":24}],"links":[{"source":48,"target":1781,"weight":9},{"source":48,"target":2335,"weight":9},{"source":48,"target":2666,"weight":9},{"source":48,"target":3334,"weight":1}]}