{"nodes":[{"name":"Tamarin Norwood: A Fine Line / *Agnes Martin*","id":5185,"group":6,"radius":5,"color":"#00D773"},{"name":"Agnes Martin","id":954,"group":1,"radius":18},{"name":"Agnes Martin","id":1977,"group":6,"radius":15},{"name":"ICA@50: Pleasing Artists And Publics Since 1963","id":3580,"group":6,"radius":120},{"name":"Becky Huff Hunter","id":3616,"group":2,"radius":7},{"name":"Tamarin Norwood","id":4430,"group":1,"radius":8}],"links":[{"source":5185,"target":954,"weight":9},{"source":5185,"target":1977,"weight":12},{"source":5185,"target":3580,"weight":12},{"source":5185,"target":3616,"weight":0},{"source":5185,"target":4430,"weight":9}]}