{"nodes":[{"name":"Donald Judd","id":753,"group":1,"radius":5,"color":"#666"},{"name":"Personal Choice: Selections from Four Penn Alumni Collections","id":1856,"group":6,"radius":29},{"name":"1967: At the Crossroads","id":1896,"group":6,"radius":39},{"name":"Painting Drawing and Sculpture of the '60s and the '70s from the Dorthy and Herbert Vogel Collection","id":1969,"group":6,"radius":108},{"name":"Plastics and New Art","id":1994,"group":6,"radius":22},{"name":"7 Sculptors","id":2007,"group":6,"radius":13}],"links":[{"source":753,"target":1856,"weight":9},{"source":753,"target":1896,"weight":9},{"source":753,"target":1969,"weight":9},{"source":753,"target":1994,"weight":9},{"source":753,"target":2007,"weight":9}]}